<document uuid="CCqCLdOO4dBmevYpKYDeg">
<meta>
<copyright>CC0/PD. No rights reserved</copyright>
<source url="https://standardebooks.org/ebooks/franklin-w-dixon/the-shore-road-mystery">Standard Ebooks</source>
<title>तटमार्गगूढकथा</title>
<author>फ्रैङ्क्लिन् डब्ल्यू. डिक्सन्</author>
<note>कृत्रिमबुद्ध्या कृतं भाषान्तरं इदं</note>
<original>
<title>The Shore Road Mystery</title>
<author>Franklin W. Dixon</author></original>
</meta>
<toc>
<ref url="stolen-cars.sa.xml" n="I">चोरितानि यानानि</ref>
<ref url="circumstantial-evidence.sa.xml" n="II">परिस्थितिजन्यप्रमाणम्</ref>
<ref url="under-suspicion.sa.xml" n="III">संदेहाधीनः</ref>
<ref url="out-on-bail.sa.xml" n="IV">प्रतिभूतौ निर्गतः</ref>
<ref url="more-thieving.sa.xml" n="V">अधिकापहरणम्</ref>
<ref url="on-the-shore-road.sa.xml" n="VI">तटमार्गे</ref>
<ref url="gus-montrose.sa.xml" n="VII">गुस् मोन्त्रोसे</ref>
<ref url="the-missing-truck.sa.xml" n="VIII">अदृष्टः ट्रकः</ref>
<ref url="following-clues.sa.xml" n="IX">अनुसरणं सूचनाः</ref>
<ref url="the-great-discovery.sa.xml" n="X">महान् आविष्कारः</ref>
<ref url="fish.sa.xml" n="XI">मत्स्यः</ref>
<ref url="the-new-car.sa.xml" n="XII">नवीनं यानम्</ref>
<ref url="in-the-locker.sa.xml" n="XIII">लोके</ref>
<ref url="montrose-again.sa.xml" n="XIV">मोन्ट्रोसः पुनः</ref>
<ref url="the-suspect.sa.xml" n="XV">संदिग्धः</ref>
<ref url="kidnaped.sa.xml" n="XVI">अपहृतम्</ref>
<ref url="the-cave.sa.xml" n="XVII">गुहा</ref>
<ref url="the-auto-thieves.sa.xml" n="XVIII">यानचोराः</ref>
<ref url="captured.sa.xml" n="XIX">गृहीतः</ref>
<ref url="tables-turned.sa.xml" n="XX">परिवर्तिताः पट्टिकाः</ref>
<ref url="at-the-farmhouse.sa.xml" n="XXI">कृषिगृहे</ref>
<ref url="the-roundup.sa.xml" n="XXII">समावर्तनम्</ref>
<ref url="the-mystery-solved.sa.xml" n="XXIII">रहस्यं समाधितम्</ref>
</toc>
</document>